odoo/addons/shopfloor_mobile_custom_example/README.rst
odoo/addons/shopfloor_mobile_custom_example/__init__.py
odoo/addons/shopfloor_mobile_custom_example/__manifest__.py
odoo/addons/shopfloor_mobile_custom_example/i18n/es_AR.po
odoo/addons/shopfloor_mobile_custom_example/i18n/shopfloor_mobile_custom_example.pot
odoo/addons/shopfloor_mobile_custom_example/readme/CONTRIBUTORS.rst
odoo/addons/shopfloor_mobile_custom_example/readme/CREDITS.rst
odoo/addons/shopfloor_mobile_custom_example/readme/DESCRIPTION.rst
odoo/addons/shopfloor_mobile_custom_example/readme/HISTORY.rst
odoo/addons/shopfloor_mobile_custom_example/readme/ROADMAP.rst
odoo/addons/shopfloor_mobile_custom_example/readme/USAGE.rst
odoo/addons/shopfloor_mobile_custom_example/static/description/icon.png
odoo/addons/shopfloor_mobile_custom_example/static/description/index.html
odoo/addons/shopfloor_mobile_custom_example/static/wms/src/scenario/checkout.js
odoo/addons/shopfloor_mobile_custom_example/templates/assets.xml
odoo13_addon_shopfloor_mobile_custom_example-13.0.1.0.1.dev5.dist-info/METADATA
odoo13_addon_shopfloor_mobile_custom_example-13.0.1.0.1.dev5.dist-info/WHEEL
odoo13_addon_shopfloor_mobile_custom_example-13.0.1.0.1.dev5.dist-info/top_level.txt
odoo13_addon_shopfloor_mobile_custom_example-13.0.1.0.1.dev5.dist-info/RECORD
